<?xml version="1.0" encoding="utf-8" ?><dwsync><file name="badbehavior_bbc.gif" server="terminus13.com//public_html/fishchicks.org/" local="3449422020" remote="12040385732" /><file name="bbc_bg.gif" server="terminus13.com//public_html/fishchicks.org/" local="3449422020" remote="12040385732" /><file name="bbc_hoverbg.gif" server="terminus13.com//public_html/fishchicks.org/" local="3449422020" remote="12040385732" /><file name="bold.gif" server="terminus13.com//public_html/fishchicks.org/" local="3449422020" remote="12040385732" /><file name="center.gif" server="terminus13.com//public_html/fishchicks.org/" local="3449422020" remote="12040385732" /><file name="code.gif" server="terminus13.com//public_html/fishchicks.org/" local="3449422020" remote="12040385732" /><file name="divider.gif" server="terminus13.com//public_html/fishchicks.org/" local="3449422020" remote="12040385732" /><file name="email.gif" server="terminus13.com//public_html/fishchicks.org/" local="3449422020" remote="12040385732" /><file name="flash.gif" server="terminus13.com//public_html/fishchicks.org/" local="3449422020" remote="12040385732" /><file name="ftp.gif" server="terminus13.com//public_html/fishchicks.org/" local="3449422020" remote="12040385732" /><file name="glow.gif" server="terminus13.com//public_html/fishchicks.org/" local="3449422020" remote="12040385732" /><file name="hr.gif" server="terminus13.com//public_html/fishchicks.org/" local="3449422020" remote="12040385732" /><file name="img.gif" server="terminus13.com//public_html/fishchicks.org/" local="3449422020" remote="12040385732" /><file name="index.php" server="terminus13.com//public_html/fishchicks.org/" local="3449422020" remote="12040385732" /><file name="italicize.gif" server="terminus13.com//public_html/fishchicks.org/" local="3449422020" remote="12040385732" /><file name="left.gif" server="terminus13.com//public_html/fishchicks.org/" local="3449422020" remote="12040385732" /><file name="list.gif" server="terminus13.com//public_html/fishchicks.org/" local="3449422020" remote="12040385732" /><file name="move.gif" server="terminus13.com//public_html/fishchicks.org/" local="3449422080" remote="12040385732" /><file name="orderlist.gif" server="terminus13.com//public_html/fishchicks.org/" local="3449422080" remote="12040385792" /><file name="pre.gif" server="terminus13.com//public_html/fishchicks.org/" local="3449422080" remote="12040385792" /><file name="quote.gif" server="terminus13.com//public_html/fishchicks.org/" local="3449422080" remote="12040385792" /><file name="resize-handle.gif" server="terminus13.com//public_html/fishchicks.org/" local="3449422080" remote="12040385792" /><file name="right.gif" server="terminus13.com//public_html/fishchicks.org/" local="3449422080" remote="12040385792" /><file name="shadow.gif" server="terminus13.com//public_html/fishchicks.org/" local="3449422080" remote="12040385792" /><file name="strike.gif" server="terminus13.com//public_html/fishchicks.org/" local="3449422080" remote="12040385792" /><file name="sub.gif" server="terminus13.com//public_html/fishchicks.org/" local="3449422080" remote="12040385792" /><file name="sup.gif" server="terminus13.com//public_html/fishchicks.org/" local="3449422080" remote="12040385792" /><file name="table.gif" server="terminus13.com//public_html/fishchicks.org/" local="3449422080" remote="12040385792" /><file name="tele.gif" server="terminus13.com//public_html/fishchicks.org/" local="3449422080" remote="12040385792" /><file name="toggle.gif" server="terminus13.com//public_html/fishchicks.org/" local="3449422080" remote="12040385792" /><file name="underline.gif" server="terminus13.com//public_html/fishchicks.org/" local="3449422080" remote="12040385792" /><file name="unformat.gif" server="terminus13.com//public_html/fishchicks.org/" local="3449422080" remote="12040385792" /><file name="url.gif" server="terminus13.com//public_html/fishchicks.org/" local="3449422080" remote="12040385792" /><file name="youtube.gif" server="terminus13.com//public_html/fishchicks.org/" local="3449422080" remote="12040385792" /></dwsync>